QuaNFS/QuantumGA.py
QuaNFS/__init__.py
QuaNFS-0.0.1.dist-info/LICENSE.txt
QuaNFS-0.0.1.dist-info/METADATA
QuaNFS-0.0.1.dist-info/WHEEL
QuaNFS-0.0.1.dist-info/top_level.txt
QuaNFS-0.0.1.dist-info/RECORD
