Metadata-Version: 2.1
Name: QuaNFS
Version: 0.0.1
Summary: A python package for implementing feature selection using quantum-based nature inspired algorithms
Home-page: https://github.com/PremSRajanampalle/QuantumBasedGeneticAlgorithm/tree/main
Author: Prem S Rajanampalle
Author-email: prem.rajanampalle@gmail.com
License-File: LICENSE.txt
